pyfixed/__init__.py
pyfixed/_version.py
pyfixed/complex.py
pyfixed/fixed.py
pyfixed/fixed_cmp.py
pyfixed/test_utils.py
pyfixed-0.3.0.dist-info/licenses/LICENSE
pyfixed-0.3.0.dist-info/METADATA
pyfixed-0.3.0.dist-info/WHEEL
pyfixed-0.3.0.dist-info/entry_points.txt
pyfixed-0.3.0.dist-info/top_level.txt
pyfixed-0.3.0.dist-info/RECORD
