Metadata-Version: 2.4
Name: pyfixed
Version: 0.3.0
Summary: Arbitrary-precision fixed-point library for Python
Author: Shachar Kraus
License-Expression: MIT
Project-URL: homepage, https://shacharkraus.gitlab.io/pyfixed
Project-URL: documentation, https://shacharkraus.gitlab.io/pyfixed
Project-URL: source, https://gitlab.com/ShacharKraus/pyfixed
Project-URL: issues, https://gitlab.com/ShacharKraus/pyfixed/-/issues
Keywords: fixed,fixed point,fixed-point
Classifier: Development Status :: 3 - Alpha
Classifier: Environment :: Console
Classifier: Framework :: Pytest
Classifier: Intended Audience :: Developers
Classifier: Intended Audience :: Science/Research
Classifier: Operating System :: OS Independent
Classifier: Programming Language :: Python :: 3
Classifier: Topic :: Scientific/Engineering :: Mathematics
Classifier: Topic :: Software Development :: Libraries
Requires-Python: >=3.12
License-File: LICENSE
Requires-Dist: matplotlib
Requires-Dist: mpmath
Requires-Dist: numpy
Provides-Extra: dev
Requires-Dist: pytest; extra == "dev"
Requires-Dist: pytest-xdist; extra == "dev"
Provides-Extra: docs
Requires-Dist: myst_parser; extra == "docs"
Requires-Dist: pydata_sphinx_theme; extra == "docs"
Requires-Dist: pytest; extra == "docs"
Requires-Dist: sphinx; extra == "docs"
Requires-Dist: sphinx_autodoc_typehints; extra == "docs"
Dynamic: license-file
